{
  "version": 2,
  "extractor": "papercropper",
  "tables": [
    {
      "url": "assets/tables/arxiv/2605.22177v1/table-001.webp",
      "caption": "",
      "page": 0,
      "index": 1,
      "width": 1442,
      "height": 899,
      "label": "Table"
    },
    {
      "url": "assets/tables/arxiv/2605.22177v1/table-002.webp",
      "caption": "",
      "page": 0,
      "index": 2,
      "width": 750,
      "height": 854,
      "label": "Table"
    },
    {
      "url": "assets/tables/arxiv/2605.22177v1/table-003.webp",
      "caption": "",
      "page": 0,
      "index": 3,
      "width": 1451,
      "height": 349,
      "label": "Table"
    },
    {
      "url": "assets/tables/arxiv/2605.22177v1/table-004.webp",
      "caption": "",
      "page": 0,
      "index": 4,
      "width": 1161,
      "height": 435,
      "label": "Table"
    },
    {
      "url": "assets/tables/arxiv/2605.22177v1/table-005.webp",
      "caption": "",
      "page": 0,
      "index": 5,
      "width": 1327,
      "height": 772,
      "label": "Table"
    },
    {
      "url": "assets/tables/arxiv/2605.22177v1/table-006.webp",
      "caption": "",
      "page": 0,
      "index": 6,
      "width": 1453,
      "height": 817,
      "label": "Table"
    },
    {
      "url": "assets/tables/arxiv/2605.22177v1/table-007.webp",
      "caption": "",
      "page": 0,
      "index": 7,
      "width": 1447,
      "height": 326,
      "label": "Table"
    },
    {
      "url": "assets/tables/arxiv/2605.22177v1/table-008.webp",
      "caption": "",
      "page": 0,
      "index": 8,
      "width": 1448,
      "height": 202,
      "label": "Table"
    },
    {
      "url": "assets/tables/arxiv/2605.22177v1/table-009.webp",
      "caption": "",
      "page": 0,
      "index": 9,
      "width": 1448,
      "height": 191,
      "label": "Table"
    },
    {
      "url": "assets/tables/arxiv/2605.22177v1/table-010.webp",
      "caption": "",
      "page": 0,
      "index": 10,
      "width": 1446,
      "height": 334,
      "label": "Table"
    },
    {
      "url": "assets/tables/arxiv/2605.22177v1/table-011.webp",
      "caption": "",
      "page": 0,
      "index": 11,
      "width": 1104,
      "height": 356,
      "label": "Table"
    },
    {
      "url": "assets/tables/arxiv/2605.22177v1/table-012.webp",
      "caption": "",
      "page": 0,
      "index": 12,
      "width": 1451,
      "height": 164,
      "label": "Table"
    }
  ]
}